.gitignore
LICENSE
README.md
requirements.txt
setup.py
.github/workflows/ci.yaml
libemg/__init__.py
libemg/animator.py
libemg/data_handler.py
libemg/datasets.py
libemg/emg_predictor.py
libemg/feature_extractor.py
libemg/feature_selector.py
libemg/filtering.py
libemg/gui.py
libemg/offline_metrics.py
libemg/shared_memory_manager.py
libemg/streamers.py
libemg/utils.py
libemg.egg-info/PKG-INFO
libemg.egg-info/SOURCES.txt
libemg.egg-info/dependency_links.txt
libemg.egg-info/requires.txt
libemg.egg-info/top_level.txt
libemg/_datasets/_3DC.py
libemg/_datasets/__init__.py
libemg/_datasets/ciil.py
libemg/_datasets/continous_transitions.py
libemg/_datasets/dataset.py
libemg/_datasets/emg2pose.py
libemg/_datasets/emg_epn612.py
libemg/_datasets/fors_emg.py
libemg/_datasets/fougner_lp.py
libemg/_datasets/grab_myo.py
libemg/_datasets/hyser.py
libemg/_datasets/intensity.py
libemg/_datasets/kaufmann_md.py
libemg/_datasets/nina_pro.py
libemg/_datasets/one_subject_emager.py
libemg/_datasets/one_subject_myo.py
libemg/_datasets/radmand_lp.py
libemg/_datasets/tmr_shirleyryanabilitylab.py
libemg/_datasets/user_compliance.py
libemg/_gui/__init__.py
libemg/_gui/_data_collection_panel.py
libemg/_gui/_data_import_panel.py
libemg/_gui/_utils.py
libemg/_streamers/_OTB_Muovi.py
libemg/_streamers/_OTB_MuoviPlus.py
libemg/_streamers/_OTB_SessantaquattroPlus.py
libemg/_streamers/_OTB_Syncstation.py
libemg/_streamers/__init__.py
libemg/_streamers/_delsys_API_streamer.py
libemg/_streamers/_delsys_streamer.py
libemg/_streamers/_emager_streamer.py
libemg/_streamers/_leap_streamer.py
libemg/_streamers/_mindrove.py
libemg/_streamers/_myo_streamer.py
libemg/_streamers/_oymotion_streamer.py
libemg/_streamers/_oymotion_windows_streamer.py
libemg/_streamers/_sifi_bridge_streamer.py
libemg/environments/__init__.py
libemg/environments/_base.py
libemg/environments/controllers.py
libemg/environments/emg_hero.py
libemg/environments/fitts.py
tests/__init__.py
tests/get_feature_values.m
tests/test_feature_extractor.py
tests/test_feature_verification.py
tests/test_offline_metrics.py
tests/test_online_classifier.py
tests/test_stream_architecture.py
