Metadata-Version: 2.1
Name: libemg
Version: 2.0.3
Summary: LibEMG - Myoelectric Control Library
Home-page: UNKNOWN
Author: Ethan Eddy, Evan Campbell, Angkoon Phinyomark, Scott Bateman, and Erik Scheme
License: UNKNOWN
Keywords: emg,myoelectric_control,pattern_recognition,muscle-based input
Platform: UNKNOWN
Classifier: Development Status :: 5 - Production/Stable  
Classifier: Intended Audience :: Developers
Classifier: Programming Language :: Python :: 3
Classifier: Operating System :: Unix
Classifier: Operating System :: MacOS :: MacOS X
Classifier: Operating System :: Microsoft :: Windows
License-File: LICENSE
